rlephant/__init__.py
rlephant/entities.py
rlephant/persistence.py
rlephant/summary/__init__.py
rlephant/summary/__main__.py
tests/__init__.py
tests/test_entities.py
tests/test_persistence.py
tests/util.py
rlephant-1.0.0.dist-info/LICENSE
rlephant-1.0.0.dist-info/METADATA
rlephant-1.0.0.dist-info/WHEEL
rlephant-1.0.0.dist-info/top_level.txt
rlephant-1.0.0.dist-info/RECORD
