Metadata-Version: 2.1
Name: rlephant
Version: 1.0.0
Summary: A simple tool to efficiently read and write episodes of MDP's to files.
Home-page: https://github.com/axelbr/rlephant
Author: Axel Brunnbauer
Author-email: axel.brunnbauer@gmx.at
License: UNKNOWN
Platform: UNKNOWN
Classifier: Programming Language :: Python :: 3
Classifier: License :: OSI Approved :: MIT License
Classifier: Operating System :: OS Independent
Requires-Python: >=3.6
Requires-Dist: numpy
Requires-Dist: h5py
